pytest_forks/__init__.py
pytest_forks/py.typed
pytest_forks-1.0.1.dist-info/LICENSE
pytest_forks-1.0.1.dist-info/METADATA
pytest_forks-1.0.1.dist-info/WHEEL
pytest_forks-1.0.1.dist-info/top_level.txt
pytest_forks-1.0.1.dist-info/RECORD
