Metadata-Version: 2.1
Name: pytest-forks
Version: 1.0.1
Summary: Fork helper for pytest
Classifier: Environment :: Plugins
Classifier: Framework :: Pytest
Classifier: Intended Audience :: Developers
Classifier: License :: OSI Approved :: The Unlicense (Unlicense)
Classifier: Operating System :: POSIX
Classifier: Programming Language :: Python :: 3
Classifier: Typing :: Typed
Requires-Python: >=3
License-File: LICENSE
